config/__init__.py
config/paths.py
config/v2_compat.py
config/v2_config.py
config/v2_sessions.py
config/v2_settings.py
core/__init__.py
core/controller.py
core/update_checker.py
core/handlers/__init__.py
core/handlers/command_handlers.py
core/handlers/message_handler.py
core/handlers/session_handler.py
core/handlers/settings_handler.py
modules/__init__.py
modules/agent_router.py
modules/claude_client.py
modules/session_manager.py
modules/settings_manager.py
modules/agents/__init__.py
modules/agents/base.py
modules/agents/claude_agent.py
modules/agents/claude_question_handler.py
modules/agents/codex_agent.py
modules/agents/opencode_agent.py
modules/agents/question_ui.py
modules/agents/service.py
modules/agents/subagent_router.py
modules/agents/opencode/__init__.py
modules/agents/opencode/agent.py
modules/agents/opencode/client_manager.py
modules/agents/opencode/message_processor.py
modules/agents/opencode/poll_loop.py
modules/agents/opencode/question_handler.py
modules/agents/opencode/server.py
modules/agents/opencode/session.py
modules/agents/opencode/types.py
modules/agents/opencode/utils.py
modules/im/__init__.py
modules/im/base.py
modules/im/factory.py
modules/im/slack.py
modules/im/formatters/__init__.py
modules/im/formatters/base_formatter.py
modules/im/formatters/slack_formatter.py
vibe/__init__.py
vibe/__main__.py
vibe/_version.py
vibe/api.py
vibe/cli.py
vibe/runtime.py
vibe/ui_server.py
vibe/templates/slack_manifest.json
vibe/service_main.py
vibe/ui/dist/index.html
vibe/ui/dist/logo.png
vibe/ui/dist/vite.svg
vibe/ui/dist/assets/index-Do852wqj.css
vibe/ui/dist/assets/index-DtTVSLIm.js
vibe/ui/dist/assets/logo-BzryTZ7u.png
vibe_remote-2.1.15.dist-info/METADATA
vibe_remote-2.1.15.dist-info/WHEEL
vibe_remote-2.1.15.dist-info/entry_points.txt
vibe_remote-2.1.15.dist-info/licenses/LICENSE
vibe_remote-2.1.15.dist-info/RECORD
