Metadata-Version: 2.4
Name: vibe-remote
Version: 2.1.15
Summary: Local-first agent runtime for Slack - run AI coding agents from your chat
Project-URL: Homepage, https://github.com/cyhhao/vibe-remote
Project-URL: Repository, https://github.com/cyhhao/vibe-remote
Project-URL: Documentation, https://github.com/cyhhao/vibe-remote#readme
Project-URL: Issues, https://github.com/cyhhao/vibe-remote/issues
Author-email: cyhhao <cyhhao@users.noreply.github.com>
License-Expression: MIT
License-File: LICENSE
Keywords: agent,ai,automation,claude,codex,opencode,slack
Classifier: Development Status :: 4 - Beta
Classifier: Environment :: Console
Classifier: Intended Audience :: Developers
Classifier: License :: OSI Approved :: MIT License
Classifier: Operating System :: OS Independent
Classifier: Programming Language :: Python :: 3
Classifier: Programming Language :: Python :: 3.10
Classifier: Programming Language :: Python :: 3.11
Classifier: Programming Language :: Python :: 3.12
Classifier: Topic :: Communications :: Chat
Classifier: Topic :: Software Development :: Libraries :: Python Modules
Requires-Python: >=3.10
Requires-Dist: aiohttp>=3.8.0
Requires-Dist: anyio>=4.0.0
Requires-Dist: claude-agent-sdk>=0.1.23
Requires-Dist: flask>=3.0.0
Requires-Dist: markdown-to-mrkdwn>=0.2.0
Requires-Dist: pyyaml>=6.0
Requires-Dist: slack-sdk>=3.26.0
Requires-Dist: typing-extensions>=4.12.2
